<?xml version="1.0" encoding="utf-8" ?><dwsync><file name="carboncopy_banner_01.png" server="sftp.uwo.ca/public_html/" local="3626307254" remote="3626914025" Dst="-1" /><file name="lamborghini_svj_01.jpg" server="sftp.uwo.ca/public_html/" local="3626310040" remote="3626914025" Dst="-1" /><file name="senna_01.jpg" server="sftp.uwo.ca/public_html/" local="3626891952" remote="3626914026" Dst="-1" /><file name="720s_01.jpg" server="sftp.uwo.ca/public_html/" local="3626892058" remote="3626914026" Dst="-1" /><file name="488_pista_01.jpg" server="sftp.uwo.ca/public_html/" local="3626891600" remote="3626914026" Dst="-1" /><file name="600lt_01.jpg" server="sftp.uwo.ca/public_html/" local="3626892106" remote="3626914026" Dst="-1" /><file name="portofino_01.jpg" server="sftp.uwo.ca/public_html/" local="3626891666" remote="3626914026" Dst="-1" /><file name="812_superfast_00.jpg" server="sftp.uwo.ca/public_html/" local="3626358568" remote="3626914026" Dst="-1" /><file name="huracan_performante_01.jpg" server="sftp.uwo.ca/public_html/" local="3626891730" remote="3626914027" Dst="-1" /><file name="gt2_rs_01.jpg" server="sftp.uwo.ca/public_html/" local="3626892164" remote="3626914027" Dst="-1" /><file name="gt3_rs_01.jpg" server="sftp.uwo.ca/public_html/" local="3626892226" remote="3626914027" Dst="-1" /><file name="gt3_01.jpg" server="sftp.uwo.ca/public_html/" local="3626892262" remote="3626914027" Dst="-1" /><file name="vantage_01.jpg" server="sftp.uwo.ca/public_html/" local="3626892306" remote="3626914027" Dst="-1" /><file name="vanquish_zagato_01.jpg" server="sftp.uwo.ca/public_html/" local="3626892356" remote="3626914027" Dst="-1" /><file name="dbs_superleggera_01.jpg" server="sftp.uwo.ca/public_html/" local="3626892398" remote="3626914028" Dst="-1" /><file name="mshay_car-50_01.jpg" server="sftp.uwo.ca/public_html/" local="3626912424" remote="3626914028" Dst="-1" /><file name="mshay_car-51_01.jpg" server="sftp.uwo.ca/public_html/" local="3626912472" remote="3626914028" Dst="-1" /><file name="mshay_car-11_01.jpg" server="sftp.uwo.ca/public_html/" local="3626912632" remote="3626914028" Dst="-1" /><file name="mshay_car-22_01.jpg" server="sftp.uwo.ca/public_html/" local="3626912702" remote="3626914028" Dst="-1" /><file name="mshay_car-24_01.jpg" server="sftp.uwo.ca/public_html/" local="3626912738" remote="3626914029" Dst="-1" /><file name="mshay_car-25_01.jpg" server="sftp.uwo.ca/public_html/" local="3626912782" remote="3626914029" Dst="-1" /><file name="mshay_car-27_01.jpg" server="sftp.uwo.ca/public_html/" local="3626912818" remote="3626914029" Dst="-1" /><file name="mshay_car-29_01.jpg" server="sftp.uwo.ca/public_html/" local="3626912862" remote="3626914030" Dst="-1" /><file name="mshay_car-42_01.jpg" server="sftp.uwo.ca/public_html/" local="3626912918" remote="3626914030" Dst="-1" /><file name="mshay_car-52_01.jpg" server="sftp.uwo.ca/public_html/" local="3626912966" remote="3626914031" Dst="-1" /><file name="mshay_car-53_01.jpg" server="sftp.uwo.ca/public_html/" local="3626913004" remote="3626914031" Dst="-1" /><file name="mshay_car-55_01.jpg" server="sftp.uwo.ca/public_html/" local="3626913044" remote="3626914032" Dst="-1" /><file name="max_01.jpg" server="sftp.uwo.ca/public_html/" local="3626915962" remote="3626916545" Dst="-1" /></dwsync>